teenycli/__init__.py
teenycli/teenycli.py
teenycli-0.1.3.dist-info/LICENSE
teenycli-0.1.3.dist-info/METADATA
teenycli-0.1.3.dist-info/WHEEL
teenycli-0.1.3.dist-info/RECORD
