Metadata-Version: 2.1
Name: teenycli
Version: 0.1.3
Summary: A tiny library for building CLIs
License: MIT
Author: Ian Fisher
Author-email: ian@iafisher.com
Requires-Python: >=3.9,<4.0
Classifier: License :: OSI Approved :: MIT License
Classifier: Programming Language :: Python :: 3
Classifier: Programming Language :: Python :: 3.9
Classifier: Programming Language :: Python :: 3.10
Classifier: Programming Language :: Python :: 3.11
Classifier: Programming Language :: Python :: 3.12
